goldenset/__init__.py
goldenset/constants.py
goldenset/exceptions.py
goldenset/goldenset.py
goldenset/utils.py
goldenset-0.0.3.dist-info/METADATA
goldenset-0.0.3.dist-info/WHEEL
goldenset-0.0.3.dist-info/RECORD
